orbiter_community_translations-0.10.1.dist-info/licenses/LICENSE
orbiter_translations/version.py
orbiter_translations/argo/__init__.py
orbiter_translations/argo/yaml_demo.py
orbiter_translations/automic/__init__.py
orbiter_translations/automic/xml_demo.py
orbiter_translations/autosys/jil_demo.py
orbiter_translations/control_m/__init__.py
orbiter_translations/control_m/xml_demo.py
orbiter_translations/cron/__init__.py
orbiter_translations/cron/crontab_base.py
orbiter_translations/cron/crontab_ssh.py
orbiter_translations/dag_factory/__init__.py
orbiter_translations/dag_factory/yaml_base.py
orbiter_translations/data_stage/__init__.py
orbiter_translations/data_stage/xml_demo.py
orbiter_translations/esp/__init__.py
orbiter_translations/esp/txt_demo.py
orbiter_translations/iwa/file_type.py
orbiter_translations/iwa/txt_demo.py
orbiter_translations/jams/__init__.py
orbiter_translations/jams/xml_demo.py
orbiter_translations/jenkins/__init__.py
orbiter_translations/jenkins/json_demo.py
orbiter_translations/kestra/__init__.py
orbiter_translations/kestra/yaml_demo.py
orbiter_translations/luigi/__init__.py
orbiter_translations/luigi/python_demo.py
orbiter_translations/matillion/__init__.py
orbiter_translations/matillion/yaml_demo.py
orbiter_translations/oozie/__init__.py
orbiter_translations/oozie/xml_demo.py
orbiter_translations/ssis/__init__.py
orbiter_translations/ssis/xml_demo.py
orbiter_translations/talend/__init__.py
orbiter_translations/talend/json_demo.py
orbiter_translations/tidal/__init__.py
orbiter_translations/tidal/xml_demo.py
orbiter_community_translations-0.10.1.dist-info/METADATA
orbiter_community_translations-0.10.1.dist-info/WHEEL
orbiter_community_translations-0.10.1.dist-info/top_level.txt
orbiter_community_translations-0.10.1.dist-info/RECORD
