Metadata-Version: 2.4
Name: orbiter-community-translations
Version: 0.10.1
Summary: Astronomer Orbiter can take your legacy workloads and land them safely down in a new home on Apache Airflow!
Author-email: Fritz Davenport <fritz@astronomer.io>, CETA Team <ceta@astronomer.io>, Astronomer <humans@astronomer.io>
License:                                  Apache License
Project-URL: Homepage, https://astronomer.io
Project-URL: Source, https://github.com/astronomer/orbiter-community-translations
Requires-Python: >=3.10
License-File: LICENSE
Requires-Dist: inflection
Requires-Dist: jinja2
Requires-Dist: jq
Requires-Dist: loguru
Requires-Dist: eval_type_backport; python_version < "3.10"
Requires-Dist: json2ast
Requires-Dist: orbiter-parsers
Provides-Extra: oozie
Requires-Dist: o2a; extra == "oozie"
Requires-Dist: o2a-lib; extra == "oozie"
Requires-Dist: lark; extra == "oozie"
Requires-Dist: apache-airflow>2.10; extra == "oozie"
Provides-Extra: dev
Requires-Dist: astronomer-orbiter>=1.8.1; extra == "dev"
Requires-Dist: build; extra == "dev"
Requires-Dist: twine>=4.0.2; extra == "dev"
Requires-Dist: mkdocs; extra == "dev"
Requires-Dist: mkdocs-click; extra == "dev"
Requires-Dist: mkdocs-material; extra == "dev"
Requires-Dist: mkdocstrings-python; extra == "dev"
Requires-Dist: pygments; extra == "dev"
Requires-Dist: pytest>=7.4; extra == "dev"
Requires-Dist: pytest-cov>=4.1; extra == "dev"
Requires-Dist: pytest-sugar>=0.9.7; extra == "dev"
Requires-Dist: pytest-mock; extra == "dev"
Requires-Dist: black>=23.12.0; extra == "dev"
Requires-Dist: ruff>=0.1.0; extra == "dev"
Requires-Dist: pylint>=3.0.0; extra == "dev"
Requires-Dist: isort>=5.13.0; extra == "dev"
Requires-Dist: pre-commit>=3.6.0; python_version >= "3.9" and extra == "dev"
Requires-Dist: detect-secrets>=1.4.0; extra == "dev"
Dynamic: license-file
